pytest_dbt/__init__.py
pytest_dbt/dbt_context.py
pytest_dbt/pytest_dbt.py
pytest_dbt/sql_exec.py
pytest_dbt-0.1.1.dist-info/LICENSE
pytest_dbt-0.1.1.dist-info/METADATA
pytest_dbt-0.1.1.dist-info/WHEEL
pytest_dbt-0.1.1.dist-info/entry_points.txt
pytest_dbt-0.1.1.dist-info/RECORD
