Metadata-Version: 2.1
Name: pytest-dbt
Version: 0.1.1
Summary: Unit test dbt models with standard python tooling
License: MPL-2.0
Author: Anup Kalburgi
Author-email: anupkalburgi@gmail.com
Requires-Python: >=3.8,<4.0
Classifier: Development Status :: 2 - Pre-Alpha
Classifier: Framework :: Pytest
Classifier: Intended Audience :: Developers
Classifier: License :: OSI Approved
Classifier: License :: OSI Approved :: MIT License
Classifier: Natural Language :: English
Classifier: Operating System :: MacOS :: MacOS X
Classifier: Operating System :: Microsoft :: Windows
Classifier: Operating System :: POSIX
Classifier: Programming Language :: Python :: 3
Classifier: Programming Language :: Python :: 3.8
Classifier: Programming Language :: Python :: 3.9
Classifier: Programming Language :: Python :: 3.10
Classifier: Programming Language :: Python :: 3.11
Classifier: Programming Language :: Python :: 3.7
Classifier: Topic :: Software Development :: Quality Assurance
Classifier: Topic :: Software Development :: Testing
Classifier: Topic :: Utilities
Requires-Dist: pandas (>=2.0.1,<3.0.0)
Requires-Dist: pytest (>=7.0.0,<8.0.0)
Requires-Dist: sqlglot (>=13.3.0,<14.0.0)
